{
	"source": "logiNonograms",
	"year" : "2018",
	"month" : "11",
	"difficulty" : 4,
	"height": 20,
	"width" : 40,
	"rowSequences" : [
		[40], [1, 25], [1, 3, 18, 2], [1, 2, 4, 6, 2], [1, 1, 1, 1, 1, 2, 1, 2, 1, 1],
		[1, 2, 1, 2, 2, 1, 1, 1], [1, 1, 1, 1, 1, 1, 2, 1], [2, 2, 6, 2, 2], [3, 6, 4, 2], [5, 4, 2, 1, 1, 1, 4, 4],
		[7, 11, 10], [4, 4, 1, 5, 5], [4, 4, 1, 1, 5, 4], [5, 3, 1, 1, 4, 4], [6, 3, 1, 2, 1, 5, 5],
		[7, 2, 2, 2, 4, 6], [9, 3, 3, 7], [18, 2, 4, 9], [18, 19], [19, 19]
	],
	"columnSequences": [
		[20], [1, 13], [1, 12], [1, 4, 11], [1, 2, 3, 2, 7],
		[1, 1, 1, 1, 6], [1, 2, 5], [1, 3, 1, 4], [2, 1, 4], [2, 2, 2, 3],
		[2, 2, 1, 3, 3], [3, 1, 1, 3, 3], [3, 1, 3, 3], [3, 1, 2, 3], [4, 1, 3, 3],
		[4, 3, 4], [5, 2, 5], [4, 2, 10], [3, 1, 2, 1], [3, 1, 1, 1, 1],
		[3, 1, 1, 1, 1], [4, 1, 1, 2], [5, 2, 2, 8], [5, 2, 5], [4, 4, 4],
		[4, 1, 2, 3], [4, 1, 2, 2], [3, 2, 4, 2], [3, 1, 1, 3, 2], [2, 2, 1, 4, 2],
		[2, 2, 3, 2], [2, 1, 1, 2, 3], [2, 3, 1, 1, 3], [1, 1, 4], [1, 1, 1, 1, 5],
		[1, 2, 2, 2, 6], [1, 4, 11], [1, 11], [1, 13], [1, 16]
	]
}